setup.py
gust/__init__.py
gust/core/__init__.py
gust/core/datamodel_pb2.py
opencannabis/__init__.py
opencannabis.egg-info/PKG-INFO
opencannabis.egg-info/SOURCES.txt
opencannabis.egg-info/dependency_links.txt
opencannabis.egg-info/requires.txt
opencannabis.egg-info/top_level.txt
opencannabis/accounting/Taxes_pb2.py
opencannabis/accounting/__init__.py
opencannabis/base/Compression_pb2.py
opencannabis/base/Language_pb2.py
opencannabis/base/ProductKey_pb2.py
opencannabis/base/ProductKind_pb2.py
opencannabis/base/__init__.py
opencannabis/commerce/Currency_pb2.py
opencannabis/commerce/Customer_pb2.py
opencannabis/commerce/Discounts_pb2.py
opencannabis/commerce/Item_pb2.py
opencannabis/commerce/Order_pb2.py
opencannabis/commerce/__init__.py
opencannabis/commerce/payments/Payment_pb2.py
opencannabis/commerce/payments/__init__.py
opencannabis/contact/ContactInfo_pb2.py
opencannabis/contact/EmailAddress_pb2.py
opencannabis/contact/PhoneNumber_pb2.py
opencannabis/contact/Website_pb2.py
opencannabis/contact/__init__.py
opencannabis/content/Brand_pb2.py
opencannabis/content/Colors_pb2.py
opencannabis/content/Content_pb2.py
opencannabis/content/Data_pb2.py
opencannabis/content/MaterialsData_pb2.py
opencannabis/content/Name_pb2.py
opencannabis/content/ProductContent_pb2.py
opencannabis/content/__init__.py
opencannabis/crypto/Container_pb2.py
opencannabis/crypto/Signature_pb2.py
opencannabis/crypto/__init__.py
opencannabis/crypto/primitives/Integrity_pb2.py
opencannabis/crypto/primitives/Keys_pb2.py
opencannabis/crypto/primitives/__init__.py
opencannabis/device/Device_pb2.py
opencannabis/device/__init__.py
opencannabis/geo/Address_pb2.py
opencannabis/geo/Country_pb2.py
opencannabis/geo/Distance_pb2.py
opencannabis/geo/Geohash_pb2.py
opencannabis/geo/Location_pb2.py
opencannabis/geo/Point_pb2.py
opencannabis/geo/Province_pb2.py
opencannabis/geo/USState_pb2.py
opencannabis/geo/__init__.py
opencannabis/inventory/InventoryLocation_pb2.py
opencannabis/inventory/InventoryProduct_pb2.py
opencannabis/inventory/__init__.py
opencannabis/inventory/rfid/LLRP_pb2.py
opencannabis/inventory/rfid/RFID_pb2.py
opencannabis/inventory/rfid/__init__.py
