Metadata-Version: 1.1
Name: opencannabis
Version: 0.0.1a8
Summary: OpenCannabis SDK for Python
Home-page: https://github.com/OpenCannabis/Python
Author: Sam Gammon
Author-email: sam.g@cookies.co
License: UNKNOWN
Platform: UNKNOWN
Classifier: Development Status :: 4 - Beta
Classifier: Intended Audience :: Developers
Classifier: License :: OSI Approved :: MIT License
Classifier: Operating System :: POSIX
Classifier: Programming Language :: Python :: 2
Classifier: Programming Language :: Python :: 2.6
Classifier: Programming Language :: Python :: 2.7
Classifier: Programming Language :: Python :: 3
Classifier: Programming Language :: Python :: 3.6
Classifier: Programming Language :: Python :: 3.7
Classifier: Programming Language :: Python :: 3.8
Requires: protobuf
Requires: colorlog
Requires: gust
